{
  "a_comp_cor_00": {
    "CumulativeVarianceExplained": 0.1618705506,
    "Mask": "CSF",
    "Method": "aCompCor",
    "Retained": true,
    "SingularValue": 64.4622285012,
    "VarianceExplained": 0.1618705506
  },
  "a_comp_cor_01": {
    "CumulativeVarianceExplained": 0.3020421397,
    "Mask": "CSF",
    "Method": "aCompCor",
    "Retained": true,
    "SingularValue": 59.9862056209,
    "VarianceExplained": 0.1401715891
  },
  "a_comp_cor_02": {
    "CumulativeVarianceExplained": 0.3854955892,
    "Mask": "CSF",
    "Method": "aCompCor",
    "Retained": true,
    "SingularValue": 46.2853486876,
    "VarianceExplained": 0.0834534495
  },
  "a_comp_cor_03": {
    "CumulativeVarianceExplained": 0.4275979697,
    "Mask": "CSF",
    "Method": "aCompCor",
    "Retained": true,
    "SingularValue": 32.8756780793,
    "VarianceExplained": 0.0421023805
  },
  "a_comp_cor_04": {
    "CumulativeVarianceExplained": 0.4637678603,
    "Mask": "CSF",
    "Method": "aCompCor",
    "Retained": true,
    "SingularValue": 30.471581194,
    "VarianceExplained": 0.0361698906
  },
  "a_comp_cor_05": {
    "CumulativeVarianceExplained": 0.4935988904,
    "Mask": "CSF",
    "Method": "aCompCor",
    "Retained": true,
    "SingularValue": 27.6729538277,
    "VarianceExplained": 0.0298310301
  },
  "a_comp_cor_06": {
    "CumulativeVarianceExplained": 0.5219882843,
    "Mask": "CSF",
    "Method": "aCompCor",
    "Retained": true,
    "SingularValue": 26.9960021241,
    "VarianceExplained": 0.0283893939
  },
  "a_comp_cor_07": {
    "CumulativeVarianceExplained": 0.086825664,
    "Mask": "WM",
    "Method": "aCompCor",
    "Retained": true,
    "SingularValue": 132.5232081918,
    "VarianceExplained": 0.086825664
  },
  "a_comp_cor_08": {
    "CumulativeVarianceExplained": 0.1459131138,
    "Mask": "WM",
    "Method": "aCompCor",
    "Retained": true,
    "SingularValue": 109.3239984505,
    "VarianceExplained": 0.0590874498
  },
  "a_comp_cor_09": {
    "CumulativeVarianceExplained": 0.1824150838,
    "Mask": "WM",
    "Method": "aCompCor",
    "Retained": true,
    "SingularValue": 85.9262851148,
    "VarianceExplained": 0.03650197
  },
  "a_comp_cor_10": {
    "CumulativeVarianceExplained": 0.2107745262,
    "Mask": "WM",
    "Method": "aCompCor",
    "Retained": true,
    "SingularValue": 75.7385050589,
    "VarianceExplained": 0.0283594425
  },
  "a_comp_cor_11": {
    "CumulativeVarianceExplained": 0.2314021486,
    "Mask": "WM",
    "Method": "aCompCor",
    "Retained": true,
    "SingularValue": 64.5940433015,
    "VarianceExplained": 0.0206276224
  },
  "a_comp_cor_12": {
    "CumulativeVarianceExplained": 0.2489658306,
    "Mask": "WM",
    "Method": "aCompCor",
    "Retained": true,
    "SingularValue": 59.6040357726,
    "VarianceExplained": 0.017563682
  },
  "a_comp_cor_13": {
    "CumulativeVarianceExplained": 0.266208655,
    "Mask": "WM",
    "Method": "aCompCor",
    "Retained": true,
    "SingularValue": 59.0570959384,
    "VarianceExplained": 0.0172428244
  },
  "a_comp_cor_14": {
    "CumulativeVarianceExplained": 0.2817230409,
    "Mask": "WM",
    "Method": "aCompCor",
    "Retained": true,
    "SingularValue": 56.018977674,
    "VarianceExplained": 0.0155143859
  },
  "a_comp_cor_15": {
    "CumulativeVarianceExplained": 0.296499296,
    "Mask": "WM",
    "Method": "aCompCor",
    "Retained": true,
    "SingularValue": 54.6701261198,
    "VarianceExplained": 0.0147762552
  },
  "a_comp_cor_16": {
    "CumulativeVarianceExplained": 0.3108039766,
    "Mask": "WM",
    "Method": "aCompCor",
    "Retained": true,
    "SingularValue": 53.7906715401,
    "VarianceExplained": 0.0143046806
  },
  "a_comp_cor_17": {
    "CumulativeVarianceExplained": 0.3246984572,
    "Mask": "WM",
    "Method": "aCompCor",
    "Retained": true,
    "SingularValue": 53.0138131308,
    "VarianceExplained": 0.0138944806
  },
  "a_comp_cor_18": {
    "CumulativeVarianceExplained": 0.337266666,
    "Mask": "WM",
    "Method": "aCompCor",
    "Retained": true,
    "SingularValue": 50.4202015877,
    "VarianceExplained": 0.0125682088
  },
  "a_comp_cor_19": {
    "CumulativeVarianceExplained": 0.3495702347,
    "Mask": "WM",
    "Method": "aCompCor",
    "Retained": true,
    "SingularValue": 49.8865457357,
    "VarianceExplained": 0.0123035687
  },
  "a_comp_cor_20": {
    "CumulativeVarianceExplained": 0.3617763258,
    "Mask": "WM",
    "Method": "aCompCor",
    "Retained": true,
    "SingularValue": 49.6885344161,
    "VarianceExplained": 0.0122060911
  },
  "a_comp_cor_21": {
    "CumulativeVarianceExplained": 0.3737510972,
    "Mask": "WM",
    "Method": "aCompCor",
    "Retained": true,
    "SingularValue": 49.2154545047,
    "VarianceExplained": 0.0119747714
  },
  "a_comp_cor_22": {
    "CumulativeVarianceExplained": 0.3851109174,
    "Mask": "WM",
    "Method": "aCompCor",
    "Retained": true,
    "SingularValue": 47.9350972822,
    "VarianceExplained": 0.0113598202
  },
  "a_comp_cor_23": {
    "CumulativeVarianceExplained": 0.3961785962,
    "Mask": "WM",
    "Method": "aCompCor",
    "Retained": true,
    "SingularValue": 47.3147073043,
    "VarianceExplained": 0.0110676788
  },
  "a_comp_cor_24": {
    "CumulativeVarianceExplained": 0.4071287472,
    "Mask": "WM",
    "Method": "aCompCor",
    "Retained": true,
    "SingularValue": 47.0628192843,
    "VarianceExplained": 0.0109501511
  },
  "a_comp_cor_25": {
    "CumulativeVarianceExplained": 0.4177832319,
    "Mask": "WM",
    "Method": "aCompCor",
    "Retained": true,
    "SingularValue": 46.4230968582,
    "VarianceExplained": 0.0106544847
  },
  "a_comp_cor_26": {
    "CumulativeVarianceExplained": 0.4280428306,
    "Mask": "WM",
    "Method": "aCompCor",
    "Retained": true,
    "SingularValue": 45.5546874321,
    "VarianceExplained": 0.0102595987
  },
  "a_comp_cor_27": {
    "CumulativeVarianceExplained": 0.4381466929,
    "Mask": "WM",
    "Method": "aCompCor",
    "Retained": true,
    "SingularValue": 45.2076147648,
    "VarianceExplained": 0.0101038623
  },
  "a_comp_cor_28": {
    "CumulativeVarianceExplained": 0.4480114302,
    "Mask": "WM",
    "Method": "aCompCor",
    "Retained": true,
    "SingularValue": 44.6694542825,
    "VarianceExplained": 0.0098647373
  },
  "a_comp_cor_29": {
    "CumulativeVarianceExplained": 0.4578213838,
    "Mask": "WM",
    "Method": "aCompCor",
    "Retained": true,
    "SingularValue": 44.5452458718,
    "VarianceExplained": 0.0098099536
  },
  "a_comp_cor_30": {
    "CumulativeVarianceExplained": 0.4672190443,
    "Mask": "WM",
    "Method": "aCompCor",
    "Retained": true,
    "SingularValue": 43.5991236539,
    "VarianceExplained": 0.0093976605
  },
  "a_comp_cor_31": {
    "CumulativeVarianceExplained": 0.4765279313,
    "Mask": "WM",
    "Method": "aCompCor",
    "Retained": true,
    "SingularValue": 43.3927091209,
    "VarianceExplained": 0.0093088871
  },
  "a_comp_cor_32": {
    "CumulativeVarianceExplained": 0.4856961556,
    "Mask": "WM",
    "Method": "aCompCor",
    "Retained": true,
    "SingularValue": 43.0636164027,
    "VarianceExplained": 0.0091682243
  },
  "a_comp_cor_33": {
    "CumulativeVarianceExplained": 0.49472458,
    "Mask": "WM",
    "Method": "aCompCor",
    "Retained": true,
    "SingularValue": 42.7340317391,
    "VarianceExplained": 0.0090284244
  },
  "a_comp_cor_34": {
    "CumulativeVarianceExplained": 0.5035610863,
    "Mask": "WM",
    "Method": "aCompCor",
    "Retained": true,
    "SingularValue": 42.2773910803,
    "VarianceExplained": 0.0088365063
  },
  "a_comp_cor_35": {
    "CumulativeVarianceExplained": 0.0856598055,
    "Mask": "combined",
    "Method": "aCompCor",
    "Retained": true,
    "SingularValue": 134.4954947144,
    "VarianceExplained": 0.0856598055
  },
  "a_comp_cor_36": {
    "CumulativeVarianceExplained": 0.1516958894,
    "Mask": "combined",
    "Method": "aCompCor",
    "Retained": true,
    "SingularValue": 118.0891102018,
    "VarianceExplained": 0.0660360839
  },
  "a_comp_cor_37": {
    "CumulativeVarianceExplained": 0.1873479032,
    "Mask": "combined",
    "Method": "aCompCor",
    "Retained": true,
    "SingularValue": 86.768327835,
    "VarianceExplained": 0.0356520138
  },
  "a_comp_cor_38": {
    "CumulativeVarianceExplained": 0.2148876237,
    "Mask": "combined",
    "Method": "aCompCor",
    "Retained": true,
    "SingularValue": 76.2603789141,
    "VarianceExplained": 0.0275397205
  },
  "a_comp_cor_39": {
    "CumulativeVarianceExplained": 0.2354854871,
    "Mask": "combined",
    "Method": "aCompCor",
    "Retained": true,
    "SingularValue": 65.9523511517,
    "VarianceExplained": 0.0205978635
  },
  "a_comp_cor_40": {
    "CumulativeVarianceExplained": 0.2531996184,
    "Mask": "combined",
    "Method": "aCompCor",
    "Retained": true,
    "SingularValue": 61.1616402164,
    "VarianceExplained": 0.0177141312
  },
  "a_comp_cor_41": {
    "CumulativeVarianceExplained": 0.2701072596,
    "Mask": "combined",
    "Method": "aCompCor",
    "Retained": true,
    "SingularValue": 59.7531365453,
    "VarianceExplained": 0.0169076413
  },
  "a_comp_cor_42": {
    "CumulativeVarianceExplained": 0.2856542719,
    "Mask": "combined",
    "Method": "aCompCor",
    "Retained": true,
    "SingularValue": 57.2984224615,
    "VarianceExplained": 0.0155470122
  },
  "a_comp_cor_43": {
    "CumulativeVarianceExplained": 0.3005081115,
    "Mask": "combined",
    "Method": "aCompCor",
    "Retained": true,
    "SingularValue": 56.0065163688,
    "VarianceExplained": 0.0148538396
  },
  "a_comp_cor_44": {
    "CumulativeVarianceExplained": 0.314701582,
    "Mask": "combined",
    "Method": "aCompCor",
    "Retained": true,
    "SingularValue": 54.7473994597,
    "VarianceExplained": 0.0141934705
  },
  "a_comp_cor_45": {
    "CumulativeVarianceExplained": 0.3285596432,
    "Mask": "combined",
    "Method": "aCompCor",
    "Retained": true,
    "SingularValue": 54.0966575062,
    "VarianceExplained": 0.0138580612
  },
  "a_comp_cor_46": {
    "CumulativeVarianceExplained": 0.3412220164,
    "Mask": "combined",
    "Method": "aCompCor",
    "Retained": true,
    "SingularValue": 51.7102634096,
    "VarianceExplained": 0.0126623732
  },
  "a_comp_cor_47": {
    "CumulativeVarianceExplained": 0.3535102584,
    "Mask": "combined",
    "Method": "aCompCor",
    "Retained": true,
    "SingularValue": 50.9406020159,
    "VarianceExplained": 0.012288242
  },
  "a_comp_cor_48": {
    "CumulativeVarianceExplained": 0.365684503,
    "Mask": "combined",
    "Method": "aCompCor",
    "Retained": true,
    "SingularValue": 50.7037645901,
    "VarianceExplained": 0.0121742445
  },
  "a_comp_cor_49": {
    "CumulativeVarianceExplained": 0.3776065846,
    "Mask": "combined",
    "Method": "aCompCor",
    "Retained": true,
    "SingularValue": 50.1759080209,
    "VarianceExplained": 0.0119220816
  },
  "a_comp_cor_50": {
    "CumulativeVarianceExplained": 0.3887769665,
    "Mask": "combined",
    "Method": "aCompCor",
    "Retained": true,
    "SingularValue": 48.5683339349,
    "VarianceExplained": 0.0111703819
  },
  "a_comp_cor_51": {
    "CumulativeVarianceExplained": 0.3998878555,
    "Mask": "combined",
    "Method": "aCompCor",
    "Retained": true,
    "SingularValue": 48.4388248784,
    "VarianceExplained": 0.011110889
  },
  "a_comp_cor_52": {
    "CumulativeVarianceExplained": 0.4106019803,
    "Mask": "combined",
    "Method": "aCompCor",
    "Retained": true,
    "SingularValue": 47.5661000886,
    "VarianceExplained": 0.0107141248
  },
  "a_comp_cor_53": {
    "CumulativeVarianceExplained": 0.4210661338,
    "Mask": "combined",
    "Method": "aCompCor",
    "Retained": true,
    "SingularValue": 47.0079426678,
    "VarianceExplained": 0.0104641534
  },
  "a_comp_cor_54": {
    "CumulativeVarianceExplained": 0.431336933,
    "Mask": "combined",
    "Method": "aCompCor",
    "Retained": true,
    "SingularValue": 46.5716168682,
    "VarianceExplained": 0.0102707993
  },
  "a_comp_cor_55": {
    "CumulativeVarianceExplained": 0.4413396524,
    "Mask": "combined",
    "Method": "aCompCor",
    "Retained": true,
    "SingularValue": 45.9598113538,
    "VarianceExplained": 0.0100027194
  },
  "a_comp_cor_56": {
    "CumulativeVarianceExplained": 0.4511446481,
    "Mask": "combined",
    "Method": "aCompCor",
    "Retained": true,
    "SingularValue": 45.5033005646,
    "VarianceExplained": 0.0098049957
  },
  "a_comp_cor_57": {
    "CumulativeVarianceExplained": 0.460870097,
    "Mask": "combined",
    "Method": "aCompCor",
    "Retained": true,
    "SingularValue": 45.3183429402,
    "VarianceExplained": 0.0097254488
  },
  "a_comp_cor_58": {
    "CumulativeVarianceExplained": 0.470313822,
    "Mask": "combined",
    "Method": "aCompCor",
    "Retained": true,
    "SingularValue": 44.6571354169,
    "VarianceExplained": 0.009443725
  },
  "a_comp_cor_59": {
    "CumulativeVarianceExplained": 0.4795912334,
    "Mask": "combined",
    "Method": "aCompCor",
    "Retained": true,
    "SingularValue": 44.2621599866,
    "VarianceExplained": 0.0092774114
  },
  "a_comp_cor_60": {
    "CumulativeVarianceExplained": 0.4885650378,
    "Mask": "combined",
    "Method": "aCompCor",
    "Retained": true,
    "SingularValue": 43.5318870056,
    "VarianceExplained": 0.0089738044
  },
  "a_comp_cor_61": {
    "CumulativeVarianceExplained": 0.497468726,
    "Mask": "combined",
    "Method": "aCompCor",
    "Retained": true,
    "SingularValue": 43.3614869066,
    "VarianceExplained": 0.0089036882
  },
  "a_comp_cor_62": {
    "CumulativeVarianceExplained": 0.506190979,
    "Mask": "combined",
    "Method": "aCompCor",
    "Retained": true,
    "SingularValue": 42.9174129311,
    "VarianceExplained": 0.008722253
  },
  "csf": {
    "Method": "Mean"
  },
  "csf_wm": {
    "Method": "Mean"
  },
  "dropped_0": {
    "CumulativeVarianceExplained": 0.5443252633,
    "Mask": "CSF",
    "Method": "aCompCor",
    "Retained": false,
    "SingularValue": 23.9460349427,
    "VarianceExplained": 0.0223369791
  },
  "dropped_1": {
    "CumulativeVarianceExplained": 0.5651234406,
    "Mask": "CSF",
    "Method": "aCompCor",
    "Retained": false,
    "SingularValue": 23.106492763,
    "VarianceExplained": 0.0207981772
  },
  "dropped_10": {
    "CumulativeVarianceExplained": 0.7012173189,
    "Mask": "CSF",
    "Method": "aCompCor",
    "Retained": false,
    "SingularValue": 17.3420995385,
    "VarianceExplained": 0.0117154928
  },
  "dropped_100": {
    "CumulativeVarianceExplained": 0.9963553163,
    "Mask": "CSF",
    "Method": "aCompCor",
    "Retained": false,
    "SingularValue": 3.0661347665,
    "VarianceExplained": 0.000366218
  },
  "dropped_101": {
    "CumulativeVarianceExplained": 0.9967139235,
    "Mask": "CSF",
    "Method": "aCompCor",
    "Retained": false,
    "SingularValue": 3.034107056,
    "VarianceExplained": 0.0003586072
  },
  "dropped_102": {
    "CumulativeVarianceExplained": 0.9970424573,
    "Mask": "CSF",
    "Method": "aCompCor",
    "Retained": false,
    "SingularValue": 2.904098721,
    "VarianceExplained": 0.0003285337
  },
  "dropped_103": {
    "CumulativeVarianceExplained": 0.9973586735,
    "Mask": "CSF",
    "Method": "aCompCor",
    "Retained": false,
    "SingularValue": 2.8491381715,
    "VarianceExplained": 0.0003162163
  },
  "dropped_104": {
    "CumulativeVarianceExplained": 0.9976618931,
    "Mask": "CSF",
    "Method": "aCompCor",
    "Retained": false,
    "SingularValue": 2.7899730233,
    "VarianceExplained": 0.0003032196
  },
  "dropped_105": {
    "CumulativeVarianceExplained": 0.9979474652,
    "Mask": "CSF",
    "Method": "aCompCor",
    "Retained": false,
    "SingularValue": 2.707567413,
    "VarianceExplained": 0.0002855721
  },
  "dropped_106": {
    "CumulativeVarianceExplained": 0.9982109863,
    "Mask": "CSF",
    "Method": "aCompCor",
    "Retained": false,
    "SingularValue": 2.6009323822,
    "VarianceExplained": 0.0002635211
  },
  "dropped_107": {
    "CumulativeVarianceExplained": 0.9984590242,
    "Mask": "CSF",
    "Method": "aCompCor",
    "Retained": false,
    "SingularValue": 2.5233673268,
    "VarianceExplained": 0.000248038
  },
  "dropped_108": {
    "CumulativeVarianceExplained": 0.9986881355,
    "Mask": "CSF",
    "Method": "aCompCor",
    "Retained": false,
    "SingularValue": 2.4251836566,
    "VarianceExplained": 0.0002291113
  },
  "dropped_109": {
    "CumulativeVarianceExplained": 0.9989004097,
    "Mask": "CSF",
    "Method": "aCompCor",
    "Retained": false,
    "SingularValue": 2.3343716752,
    "VarianceExplained": 0.0002122742
  },
  "dropped_11": {
    "CumulativeVarianceExplained": 0.7123099379,
    "Mask": "CSF",
    "Method": "aCompCor",
    "Retained": false,
    "SingularValue": 16.8747925022,
    "VarianceExplained": 0.011092619
  },
  "dropped_110": {
    "CumulativeVarianceExplained": 0.9990961953,
    "Mask": "CSF",
    "Method": "aCompCor",
    "Retained": false,
    "SingularValue": 2.2418768914,
    "VarianceExplained": 0.0001957856
  },
  "dropped_111": {
    "CumulativeVarianceExplained": 0.9992687533,
    "Mask": "CSF",
    "Method": "aCompCor",
    "Retained": false,
    "SingularValue": 2.1046939426,
    "VarianceExplained": 0.000172558
  },
  "dropped_112": {
    "CumulativeVarianceExplained": 0.9994205853,
    "Mask": "CSF",
    "Method": "aCompCor",
    "Retained": false,
    "SingularValue": 1.9742539172,
    "VarianceExplained": 0.000151832
  },
  "dropped_113": {
    "CumulativeVarianceExplained": 0.9995663714,
    "Mask": "CSF",
    "Method": "aCompCor",
    "Retained": false,
    "SingularValue": 1.9345481,
    "VarianceExplained": 0.0001457862
  },
  "dropped_114": {
    "CumulativeVarianceExplained": 0.9997051355,
    "Mask": "CSF",
    "Method": "aCompCor",
    "Retained": false,
    "SingularValue": 1.8873822419,
    "VarianceExplained": 0.000138764
  },
  "dropped_115": {
    "CumulativeVarianceExplained": 0.999819447,
    "Mask": "CSF",
    "Method": "aCompCor",
    "Retained": false,
    "SingularValue": 1.7130351986,
    "VarianceExplained": 0.0001143115
  },
  "dropped_116": {
    "CumulativeVarianceExplained": 0.9999225424,
    "Mask": "CSF",
    "Method": "aCompCor",
    "Retained": false,
    "SingularValue": 1.6268259841,
    "VarianceExplained": 0.0001030954
  },
  "dropped_117": {
    "CumulativeVarianceExplained": 1.0,
    "Mask": "CSF",
    "Method": "aCompCor",
    "Retained": false,
    "SingularValue": 1.4101115008,
    "VarianceExplained": 7.74576e-05
  },
  "dropped_118": {
    "CumulativeVarianceExplained": 1.0,
    "Mask": "CSF",
    "Method": "aCompCor",
    "Retained": false,
    "SingularValue": 0.0,
    "VarianceExplained": 0.0
  },
  "dropped_119": {
    "CumulativeVarianceExplained": 1.0,
    "Mask": "CSF",
    "Method": "aCompCor",
    "Retained": false,
    "SingularValue": 0.0,
    "VarianceExplained": 0.0
  },
  "dropped_12": {
    "CumulativeVarianceExplained": 0.7223403682,
    "Mask": "CSF",
    "Method": "aCompCor",
    "Retained": false,
    "SingularValue": 16.0465316114,
    "VarianceExplained": 0.0100304303
  },
  "dropped_120": {
    "CumulativeVarianceExplained": 1.0,
    "Mask": "CSF",
    "Method": "aCompCor",
    "Retained": false,
    "SingularValue": 0.0,
    "VarianceExplained": 0.0
  },
  "dropped_121": {
    "CumulativeVarianceExplained": 1.0,
    "Mask": "CSF",
    "Method": "aCompCor",
    "Retained": false,
    "SingularValue": 0.0,
    "VarianceExplained": 0.0
  },
  "dropped_122": {
    "CumulativeVarianceExplained": 0.5122891705,
    "Mask": "WM",
    "Method": "aCompCor",
    "Retained": false,
    "SingularValue": 42.0172232006,
    "VarianceExplained": 0.0087280842
  },
  "dropped_123": {
    "CumulativeVarianceExplained": 0.5207896719,
    "Mask": "WM",
    "Method": "aCompCor",
    "Retained": false,
    "SingularValue": 41.4658103111,
    "VarianceExplained": 0.0085005014
  },
  "dropped_124": {
    "CumulativeVarianceExplained": 0.5292403117,
    "Mask": "WM",
    "Method": "aCompCor",
    "Retained": false,
    "SingularValue": 41.3440177119,
    "VarianceExplained": 0.0084506397
  },
  "dropped_125": {
    "CumulativeVarianceExplained": 0.5375845189,
    "Mask": "WM",
    "Method": "aCompCor",
    "Retained": false,
    "SingularValue": 41.082836977,
    "VarianceExplained": 0.0083442073
  },
  "dropped_126": {
    "CumulativeVarianceExplained": 0.5458602324,
    "Mask": "WM",
    "Method": "aCompCor",
    "Retained": false,
    "SingularValue": 40.9138742582,
    "VarianceExplained": 0.0082757134
  },
  "dropped_127": {
    "CumulativeVarianceExplained": 0.5539803359,
    "Mask": "WM",
    "Method": "aCompCor",
    "Retained": false,
    "SingularValue": 40.5273929132,
    "VarianceExplained": 0.0081201035
  },
  "dropped_128": {
    "CumulativeVarianceExplained": 0.5619960366,
    "Mask": "WM",
    "Method": "aCompCor",
    "Retained": false,
    "SingularValue": 40.2660131835,
    "VarianceExplained": 0.0080157007
  },
  "dropped_129": {
    "CumulativeVarianceExplained": 0.569943608,
    "Mask": "WM",
    "Method": "aCompCor",
    "Retained": false,
    "SingularValue": 40.0945277714,
    "VarianceExplained": 0.0079475714
  },
  "dropped_13": {
    "CumulativeVarianceExplained": 0.7322033193,
    "Mask": "CSF",
    "Method": "aCompCor",
    "Retained": false,
    "SingularValue": 15.9120023166,
    "VarianceExplained": 0.0098629511
  },
  "dropped_130": {
    "CumulativeVarianceExplained": 0.5777978139,
    "Mask": "WM",
    "Method": "aCompCor",
    "Retained": false,
    "SingularValue": 39.8583234474,
    "VarianceExplained": 0.007854206
  },
  "dropped_131": {
    "CumulativeVarianceExplained": 0.5854008444,
    "Mask": "WM",
    "Method": "aCompCor",
    "Retained": false,
    "SingularValue": 39.2158154324,
    "VarianceExplained": 0.0076030305
  },
  "dropped_132": {
    "CumulativeVarianceExplained": 0.5929266272,
    "Mask": "WM",
    "Method": "aCompCor",
    "Retained": false,
    "SingularValue": 39.0160880958,
    "VarianceExplained": 0.0075257828
  },
  "dropped_133": {
    "CumulativeVarianceExplained": 0.6003964375,
    "Mask": "WM",
    "Method": "aCompCor",
    "Retained": false,
    "SingularValue": 38.8707277769,
    "VarianceExplained": 0.0074698103
  },
  "dropped_134": {
    "CumulativeVarianceExplained": 0.6077900151,
    "Mask": "WM",
    "Method": "aCompCor",
    "Retained": false,
    "SingularValue": 38.6718723916,
    "VarianceExplained": 0.0073935775
  },
  "dropped_135": {
    "CumulativeVarianceExplained": 0.6150751305,
    "Mask": "WM",
    "Method": "aCompCor",
    "Retained": false,
    "SingularValue": 38.3871705998,
    "VarianceExplained": 0.0072851154
  },
  "dropped_136": {
    "CumulativeVarianceExplained": 0.622327274,
    "Mask": "WM",
    "Method": "aCompCor",
    "Retained": false,
    "SingularValue": 38.3002032976,
    "VarianceExplained": 0.0072521435
  },
  "dropped_137": {
    "CumulativeVarianceExplained": 0.629464306,
    "Mask": "WM",
    "Method": "aCompCor",
    "Retained": false,
    "SingularValue": 37.9950225708,
    "VarianceExplained": 0.007137032
  },
  "dropped_138": {
    "CumulativeVarianceExplained": 0.6365240973,
    "Mask": "WM",
    "Method": "aCompCor",
    "Retained": false,
    "SingularValue": 37.7888623128,
    "VarianceExplained": 0.0070597913
  },
  "dropped_139": {
    "CumulativeVarianceExplained": 0.6435603773,
    "Mask": "WM",
    "Method": "aCompCor",
    "Retained": false,
    "SingularValue": 37.725885372,
    "VarianceExplained": 0.00703628
  },
  "dropped_14": {
    "CumulativeVarianceExplained": 0.741827682,
    "Mask": "CSF",
    "Method": "aCompCor",
    "Retained": false,
    "SingularValue": 15.7183655131,
    "VarianceExplained": 0.0096243627
  },
  "dropped_140": {
    "CumulativeVarianceExplained": 0.6504519664,
    "Mask": "WM",
    "Method": "aCompCor",
    "Retained": false,
    "SingularValue": 37.3359814484,
    "VarianceExplained": 0.0068915891
  },
  "dropped_141": {
    "CumulativeVarianceExplained": 0.6572946572,
    "Mask": "WM",
    "Method": "aCompCor",
    "Retained": false,
    "SingularValue": 37.2032894766,
    "VarianceExplained": 0.0068426908
  },
  "dropped_142": {
    "CumulativeVarianceExplained": 0.6640813892,
    "Mask": "WM",
    "Method": "aCompCor",
    "Retained": false,
    "SingularValue": 37.0508550619,
    "VarianceExplained": 0.006786732
  },
  "dropped_143": {
    "CumulativeVarianceExplained": 0.6707517699,
    "Mask": "WM",
    "Method": "aCompCor",
    "Retained": false,
    "SingularValue": 36.7318830597,
    "VarianceExplained": 0.0066703806
  },
  "dropped_144": {
    "CumulativeVarianceExplained": 0.6773780804,
    "Mask": "WM",
    "Method": "aCompCor",
    "Retained": false,
    "SingularValue": 36.6103411761,
    "VarianceExplained": 0.0066263105
  },
  "dropped_145": {
    "CumulativeVarianceExplained": 0.6838934732,
    "Mask": "WM",
    "Method": "aCompCor",
    "Retained": false,
    "SingularValue": 36.3026379443,
    "VarianceExplained": 0.0065153927
  },
  "dropped_146": {
    "CumulativeVarianceExplained": 0.6902813039,
    "Mask": "WM",
    "Method": "aCompCor",
    "Retained": false,
    "SingularValue": 35.9455045684,
    "VarianceExplained": 0.0063878307
  },
  "dropped_147": {
    "CumulativeVarianceExplained": 0.6965900209,
    "Mask": "WM",
    "Method": "aCompCor",
    "Retained": false,
    "SingularValue": 35.7222171869,
    "VarianceExplained": 0.006308717
  },
  "dropped_148": {
    "CumulativeVarianceExplained": 0.702799223,
    "Mask": "WM",
    "Method": "aCompCor",
    "Retained": false,
    "SingularValue": 35.4393529183,
    "VarianceExplained": 0.0062092021
  },
  "dropped_149": {
    "CumulativeVarianceExplained": 0.7089532428,
    "Mask": "WM",
    "Method": "aCompCor",
    "Retained": false,
    "SingularValue": 35.2815234074,
    "VarianceExplained": 0.0061540198
  },
  "dropped_15": {
    "CumulativeVarianceExplained": 0.7510246042,
    "Mask": "CSF",
    "Method": "aCompCor",
    "Retained": false,
    "SingularValue": 15.3653568462,
    "VarianceExplained": 0.0091969222
  },
  "dropped_150": {
    "CumulativeVarianceExplained": 0.7150745097,
    "Mask": "WM",
    "Method": "aCompCor",
    "Retained": false,
    "SingularValue": 35.1875106167,
    "VarianceExplained": 0.0061212669
  },
  "dropped_151": {
    "CumulativeVarianceExplained": 0.7211311576,
    "Mask": "WM",
    "Method": "aCompCor",
    "Retained": false,
    "SingularValue": 35.0012896719,
    "VarianceExplained": 0.0060566479
  },
  "dropped_152": {
    "CumulativeVarianceExplained": 0.7271115294,
    "Mask": "WM",
    "Method": "aCompCor",
    "Retained": false,
    "SingularValue": 34.7801920917,
    "VarianceExplained": 0.0059803718
  },
  "dropped_153": {
    "CumulativeVarianceExplained": 0.7330509881,
    "Mask": "WM",
    "Method": "aCompCor",
    "Retained": false,
    "SingularValue": 34.6610183984,
    "VarianceExplained": 0.0059394587
  },
  "dropped_154": {
    "CumulativeVarianceExplained": 0.7389447843,
    "Mask": "WM",
    "Method": "aCompCor",
    "Retained": false,
    "SingularValue": 34.5275243133,
    "VarianceExplained": 0.0058937962
  },
  "dropped_155": {
    "CumulativeVarianceExplained": 0.7447156983,
    "Mask": "WM",
    "Method": "aCompCor",
    "Retained": false,
    "SingularValue": 34.1656891182,
    "VarianceExplained": 0.005770914
  },
  "dropped_156": {
    "CumulativeVarianceExplained": 0.7504559565,
    "Mask": "WM",
    "Method": "aCompCor",
    "Retained": false,
    "SingularValue": 34.0748223349,
    "VarianceExplained": 0.0057402583
  },
  "dropped_157": {
    "CumulativeVarianceExplained": 0.7561901939,
    "Mask": "WM",
    "Method": "aCompCor",
    "Retained": false,
    "SingularValue": 34.0569473524,
    "VarianceExplained": 0.0057342374
  },
  "dropped_158": {
    "CumulativeVarianceExplained": 0.7617950021,
    "Mask": "WM",
    "Method": "aCompCor",
    "Retained": false,
    "SingularValue": 33.6703989818,
    "VarianceExplained": 0.0056048082
  },
  "dropped_159": {
    "CumulativeVarianceExplained": 0.7673781239,
    "Mask": "WM",
    "Method": "aCompCor",
    "Retained": false,
    "SingularValue": 33.6051961836,
    "VarianceExplained": 0.0055831218
  },
  "dropped_16": {
    "CumulativeVarianceExplained": 0.7599417448,
    "Mask": "CSF",
    "Method": "aCompCor",
    "Retained": false,
    "SingularValue": 15.1298352806,
    "VarianceExplained": 0.0089171406
  },
  "dropped_160": {
    "CumulativeVarianceExplained": 0.7728662404,
    "Mask": "WM",
    "Method": "aCompCor",
    "Retained": false,
    "SingularValue": 33.3180476004,
    "VarianceExplained": 0.0054881165
  },
  "dropped_161": {
    "CumulativeVarianceExplained": 0.7782800268,
    "Mask": "WM",
    "Method": "aCompCor",
    "Retained": false,
    "SingularValue": 33.0916514855,
    "VarianceExplained": 0.0054137864
  },
  "dropped_162": {
    "CumulativeVarianceExplained": 0.7836483565,
    "Mask": "WM",
    "Method": "aCompCor",
    "Retained": false,
    "SingularValue": 32.9524322466,
    "VarianceExplained": 0.0053683297
  },
  "dropped_163": {
    "CumulativeVarianceExplained": 0.7889567019,
    "Mask": "WM",
    "Method": "aCompCor",
    "Retained": false,
    "SingularValue": 32.7678142234,
    "VarianceExplained": 0.0053083454
  },
  "dropped_164": {
    "CumulativeVarianceExplained": 0.7942639701,
    "Mask": "WM",
    "Method": "aCompCor",
    "Retained": false,
    "SingularValue": 32.7644891755,
    "VarianceExplained": 0.0053072682
  },
  "dropped_165": {
    "CumulativeVarianceExplained": 0.7994376669,
    "Mask": "WM",
    "Method": "aCompCor",
    "Retained": false,
    "SingularValue": 32.3495595768,
    "VarianceExplained": 0.0051736968
  },
  "dropped_166": {
    "CumulativeVarianceExplained": 0.8045454796,
    "Mask": "WM",
    "Method": "aCompCor",
    "Retained": false,
    "SingularValue": 32.1429228882,
    "VarianceExplained": 0.0051078127
  },
  "dropped_167": {
    "CumulativeVarianceExplained": 0.8096122787,
    "Mask": "WM",
    "Method": "aCompCor",
    "Retained": false,
    "SingularValue": 32.0136154859,
    "VarianceExplained": 0.005066799
  },
  "dropped_168": {
    "CumulativeVarianceExplained": 0.814655911,
    "Mask": "WM",
    "Method": "aCompCor",
    "Retained": false,
    "SingularValue": 31.9403442852,
    "VarianceExplained": 0.0050436323
  },
  "dropped_169": {
    "CumulativeVarianceExplained": 0.8196121376,
    "Mask": "WM",
    "Method": "aCompCor",
    "Retained": false,
    "SingularValue": 31.662372951,
    "VarianceExplained": 0.0049562266
  },
  "dropped_17": {
    "CumulativeVarianceExplained": 0.7685005067,
    "Mask": "CSF",
    "Method": "aCompCor",
    "Retained": false,
    "SingularValue": 14.8226844847,
    "VarianceExplained": 0.0085587618
  },
  "dropped_170": {
    "CumulativeVarianceExplained": 0.8245210053,
    "Mask": "WM",
    "Method": "aCompCor",
    "Retained": false,
    "SingularValue": 31.51073623,
    "VarianceExplained": 0.0049088678
  },
  "dropped_171": {
    "CumulativeVarianceExplained": 0.8293325403,
    "Mask": "WM",
    "Method": "aCompCor",
    "Retained": false,
    "SingularValue": 31.1967755566,
    "VarianceExplained": 0.004811535
  },
  "dropped_172": {
    "CumulativeVarianceExplained": 0.8340828061,
    "Mask": "WM",
    "Method": "aCompCor",
    "Retained": false,
    "SingularValue": 30.9975123626,
    "VarianceExplained": 0.0047502658
  },
  "dropped_173": {
    "CumulativeVarianceExplained": 0.8387994484,
    "Mask": "WM",
    "Method": "aCompCor",
    "Retained": false,
    "SingularValue": 30.8876134945,
    "VarianceExplained": 0.0047166423
  },
  "dropped_174": {
    "CumulativeVarianceExplained": 0.8434832997,
    "Mask": "WM",
    "Method": "aCompCor",
    "Retained": false,
    "SingularValue": 30.7800578702,
    "VarianceExplained": 0.0046838513
  },
  "dropped_175": {
    "CumulativeVarianceExplained": 0.8480995778,
    "Mask": "WM",
    "Method": "aCompCor",
    "Retained": false,
    "SingularValue": 30.5572217389,
    "VarianceExplained": 0.0046162781
  },
  "dropped_176": {
    "CumulativeVarianceExplained": 0.8526871264,
    "Mask": "WM",
    "Method": "aCompCor",
    "Retained": false,
    "SingularValue": 30.4619867054,
    "VarianceExplained": 0.0045875486
  },
  "dropped_177": {
    "CumulativeVarianceExplained": 0.8572041615,
    "Mask": "WM",
    "Method": "aCompCor",
    "Retained": false,
    "SingularValue": 30.2269702522,
    "VarianceExplained": 0.0045170351
  },
  "dropped_178": {
    "CumulativeVarianceExplained": 0.8616769884,
    "Mask": "WM",
    "Method": "aCompCor",
    "Retained": false,
    "SingularValue": 30.0786909138,
    "VarianceExplained": 0.0044728269
  },
  "dropped_179": {
    "CumulativeVarianceExplained": 0.8660854923,
    "Mask": "WM",
    "Method": "aCompCor",
    "Retained": false,
    "SingularValue": 29.8616290601,
    "VarianceExplained": 0.0044085038
  },
  "dropped_18": {
    "CumulativeVarianceExplained": 0.776366951,
    "Mask": "CSF",
    "Method": "aCompCor",
    "Retained": false,
    "SingularValue": 14.2105416238,
    "VarianceExplained": 0.0078664444
  },
  "dropped_180": {
    "CumulativeVarianceExplained": 0.8704207217,
    "Mask": "WM",
    "Method": "aCompCor",
    "Retained": false,
    "SingularValue": 29.6124218131,
    "VarianceExplained": 0.0043352294
  },
  "dropped_181": {
    "CumulativeVarianceExplained": 0.8747214919,
    "Mask": "WM",
    "Method": "aCompCor",
    "Retained": false,
    "SingularValue": 29.4944975218,
    "VarianceExplained": 0.0043007702
  },
  "dropped_182": {
    "CumulativeVarianceExplained": 0.8789589739,
    "Mask": "WM",
    "Method": "aCompCor",
    "Retained": false,
    "SingularValue": 29.2766795831,
    "VarianceExplained": 0.004237482
  },
  "dropped_183": {
    "CumulativeVarianceExplained": 0.8831795892,
    "Mask": "WM",
    "Method": "aCompCor",
    "Retained": false,
    "SingularValue": 29.2183553001,
    "VarianceExplained": 0.0042206152
  },
  "dropped_184": {
    "CumulativeVarianceExplained": 0.8873750549,
    "Mask": "WM",
    "Method": "aCompCor",
    "Retained": false,
    "SingularValue": 29.1311730999,
    "VarianceExplained": 0.0041954657
  },
  "dropped_185": {
    "CumulativeVarianceExplained": 0.8914921906,
    "Mask": "WM",
    "Method": "aCompCor",
    "Retained": false,
    "SingularValue": 28.8579497812,
    "VarianceExplained": 0.0041171357
  },
  "dropped_186": {
    "CumulativeVarianceExplained": 0.8955112279,
    "Mask": "WM",
    "Method": "aCompCor",
    "Retained": false,
    "SingularValue": 28.5120802871,
    "VarianceExplained": 0.0040190373
  },
  "dropped_187": {
    "CumulativeVarianceExplained": 0.8994826166,
    "Mask": "WM",
    "Method": "aCompCor",
    "Retained": false,
    "SingularValue": 28.3425604155,
    "VarianceExplained": 0.0039713887
  },
  "dropped_188": {
    "CumulativeVarianceExplained": 0.9034114472,
    "Mask": "WM",
    "Method": "aCompCor",
    "Retained": false,
    "SingularValue": 28.190289583,
    "VarianceExplained": 0.0039288306
  },
  "dropped_189": {
    "CumulativeVarianceExplained": 0.9073083745,
    "Mask": "WM",
    "Method": "aCompCor",
    "Retained": false,
    "SingularValue": 28.075599311,
    "VarianceExplained": 0.0038969273
  },
  "dropped_19": {
    "CumulativeVarianceExplained": 0.7840906136,
    "Mask": "CSF",
    "Method": "aCompCor",
    "Retained": false,
    "SingularValue": 14.0809851533,
    "VarianceExplained": 0.0077236626
  },
  "dropped_190": {
    "CumulativeVarianceExplained": 0.911184551,
    "Mask": "WM",
    "Method": "aCompCor",
    "Retained": false,
    "SingularValue": 28.0007495632,
    "VarianceExplained": 0.0038761765
  },
  "dropped_191": {
    "CumulativeVarianceExplained": 0.9149874644,
    "Mask": "WM",
    "Method": "aCompCor",
    "Retained": false,
    "SingularValue": 27.7348677909,
    "VarianceExplained": 0.0038029134
  },
  "dropped_192": {
    "CumulativeVarianceExplained": 0.9187044433,
    "Mask": "WM",
    "Method": "aCompCor",
    "Retained": false,
    "SingularValue": 27.4197148632,
    "VarianceExplained": 0.0037169789
  },
  "dropped_193": {
    "CumulativeVarianceExplained": 0.9224037787,
    "Mask": "WM",
    "Method": "aCompCor",
    "Retained": false,
    "SingularValue": 27.3545603532,
    "VarianceExplained": 0.0036993354
  },
  "dropped_194": {
    "CumulativeVarianceExplained": 0.9260240522,
    "Mask": "WM",
    "Method": "aCompCor",
    "Retained": false,
    "SingularValue": 27.0606717382,
    "VarianceExplained": 0.0036202735
  },
  "dropped_195": {
    "CumulativeVarianceExplained": 0.9296243844,
    "Mask": "WM",
    "Method": "aCompCor",
    "Retained": false,
    "SingularValue": 26.9860408271,
    "VarianceExplained": 0.0036003322
  },
  "dropped_196": {
    "CumulativeVarianceExplained": 0.9332024108,
    "Mask": "WM",
    "Method": "aCompCor",
    "Retained": false,
    "SingularValue": 26.9023149987,
    "VarianceExplained": 0.0035780264
  },
  "dropped_197": {
    "CumulativeVarianceExplained": 0.9367576698,
    "Mask": "WM",
    "Method": "aCompCor",
    "Retained": false,
    "SingularValue": 26.8165873009,
    "VarianceExplained": 0.003555259
  },
  "dropped_198": {
    "CumulativeVarianceExplained": 0.9402700386,
    "Mask": "WM",
    "Method": "aCompCor",
    "Retained": false,
    "SingularValue": 26.6543401384,
    "VarianceExplained": 0.0035123687
  },
  "dropped_199": {
    "CumulativeVarianceExplained": 0.9437377537,
    "Mask": "WM",
    "Method": "aCompCor",
    "Retained": false,
    "SingularValue": 26.4843667157,
    "VarianceExplained": 0.0034677152
  },
  "dropped_2": {
    "CumulativeVarianceExplained": 0.5846652815,
    "Mask": "CSF",
    "Method": "aCompCor",
    "Retained": false,
    "SingularValue": 22.3977364631,
    "VarianceExplained": 0.0195418409
  },
  "dropped_20": {
    "CumulativeVarianceExplained": 0.7915360136,
    "Mask": "CSF",
    "Method": "aCompCor",
    "Retained": false,
    "SingularValue": 13.8250086162,
    "VarianceExplained": 0.0074454
  },
  "dropped_200": {
    "CumulativeVarianceExplained": 0.9471004997,
    "Mask": "WM",
    "Method": "aCompCor",
    "Retained": false,
    "SingularValue": 26.080440098,
    "VarianceExplained": 0.003362746
  },
  "dropped_201": {
    "CumulativeVarianceExplained": 0.950421439,
    "Mask": "WM",
    "Method": "aCompCor",
    "Retained": false,
    "SingularValue": 25.9178131637,
    "VarianceExplained": 0.0033209393
  },
  "dropped_202": {
    "CumulativeVarianceExplained": 0.9537192038,
    "Mask": "WM",
    "Method": "aCompCor",
    "Retained": false,
    "SingularValue": 25.8272236355,
    "VarianceExplained": 0.0032977648
  },
  "dropped_203": {
    "CumulativeVarianceExplained": 0.9569976662,
    "Mask": "WM",
    "Method": "aCompCor",
    "Retained": false,
    "SingularValue": 25.7515268695,
    "VarianceExplained": 0.0032784623
  },
  "dropped_204": {
    "CumulativeVarianceExplained": 0.9602186748,
    "Mask": "WM",
    "Method": "aCompCor",
    "Retained": false,
    "SingularValue": 25.5248871511,
    "VarianceExplained": 0.0032210087
  },
  "dropped_205": {
    "CumulativeVarianceExplained": 0.9633985607,
    "Mask": "WM",
    "Method": "aCompCor",
    "Retained": false,
    "SingularValue": 25.3614247867,
    "VarianceExplained": 0.0031798858
  },
  "dropped_206": {
    "CumulativeVarianceExplained": 0.9665483887,
    "Mask": "WM",
    "Method": "aCompCor",
    "Retained": false,
    "SingularValue": 25.2412761169,
    "VarianceExplained": 0.0031498281
  },
  "dropped_207": {
    "CumulativeVarianceExplained": 0.9696775555,
    "Mask": "WM",
    "Method": "aCompCor",
    "Retained": false,
    "SingularValue": 25.1583549677,
    "VarianceExplained": 0.0031291668
  },
  "dropped_208": {
    "CumulativeVarianceExplained": 0.972781828,
    "Mask": "WM",
    "Method": "aCompCor",
    "Retained": false,
    "SingularValue": 25.0580805387,
    "VarianceExplained": 0.0031042725
  },
  "dropped_209": {
    "CumulativeVarianceExplained": 0.9757773249,
    "Mask": "WM",
    "Method": "aCompCor",
    "Retained": false,
    "SingularValue": 24.6151409298,
    "VarianceExplained": 0.002995497
  },
  "dropped_21": {
    "CumulativeVarianceExplained": 0.7986985889,
    "Mask": "CSF",
    "Method": "aCompCor",
    "Retained": false,
    "SingularValue": 13.5598845545,
    "VarianceExplained": 0.0071625752
  },
  "dropped_210": {
    "CumulativeVarianceExplained": 0.978693908,
    "Mask": "WM",
    "Method": "aCompCor",
    "Retained": false,
    "SingularValue": 24.2887440655,
    "VarianceExplained": 0.0029165831
  },
  "dropped_211": {
    "CumulativeVarianceExplained": 0.9815453431,
    "Mask": "WM",
    "Method": "aCompCor",
    "Retained": false,
    "SingularValue": 24.0159422293,
    "VarianceExplained": 0.0028514351
  },
  "dropped_212": {
    "CumulativeVarianceExplained": 0.9843692571,
    "Mask": "WM",
    "Method": "aCompCor",
    "Retained": false,
    "SingularValue": 23.8997643724,
    "VarianceExplained": 0.002823914
  },
  "dropped_213": {
    "CumulativeVarianceExplained": 0.9871737356,
    "Mask": "WM",
    "Method": "aCompCor",
    "Retained": false,
    "SingularValue": 23.8173772828,
    "VarianceExplained": 0.0028044784
  },
  "dropped_214": {
    "CumulativeVarianceExplained": 0.9898597765,
    "Mask": "WM",
    "Method": "aCompCor",
    "Retained": false,
    "SingularValue": 23.3090298251,
    "VarianceExplained": 0.0026860409
  },
  "dropped_215": {
    "CumulativeVarianceExplained": 0.9924995892,
    "Mask": "WM",
    "Method": "aCompCor",
    "Retained": false,
    "SingularValue": 23.1075789686,
    "VarianceExplained": 0.0026398128
  },
  "dropped_216": {
    "CumulativeVarianceExplained": 0.9951017857,
    "Mask": "WM",
    "Method": "aCompCor",
    "Retained": false,
    "SingularValue": 22.9423512605,
    "VarianceExplained": 0.0026021965
  },
  "dropped_217": {
    "CumulativeVarianceExplained": 0.9975683132,
    "Mask": "WM",
    "Method": "aCompCor",
    "Retained": false,
    "SingularValue": 22.3362808146,
    "VarianceExplained": 0.0024665275
  },
  "dropped_218": {
    "CumulativeVarianceExplained": 1.0,
    "Mask": "WM",
    "Method": "aCompCor",
    "Retained": false,
    "SingularValue": 22.1779656813,
    "VarianceExplained": 0.0024316868
  },
  "dropped_219": {
    "CumulativeVarianceExplained": 1.0,
    "Mask": "WM",
    "Method": "aCompCor",
    "Retained": false,
    "SingularValue": 0.0,
    "VarianceExplained": 0.0
  },
  "dropped_22": {
    "CumulativeVarianceExplained": 0.805574522,
    "Mask": "CSF",
    "Method": "aCompCor",
    "Retained": false,
    "SingularValue": 13.2857848526,
    "VarianceExplained": 0.0068759331
  },
  "dropped_220": {
    "CumulativeVarianceExplained": 1.0,
    "Mask": "WM",
    "Method": "aCompCor",
    "Retained": false,
    "SingularValue": 0.0,
    "VarianceExplained": 0.0
  },
  "dropped_221": {
    "CumulativeVarianceExplained": 1.0,
    "Mask": "WM",
    "Method": "aCompCor",
    "Retained": false,
    "SingularValue": 0.0,
    "VarianceExplained": 0.0
  },
  "dropped_222": {
    "CumulativeVarianceExplained": 1.0,
    "Mask": "WM",
    "Method": "aCompCor",
    "Retained": false,
    "SingularValue": 0.0,
    "VarianceExplained": 0.0
  },
  "dropped_223": {
    "CumulativeVarianceExplained": 0.5148759283,
    "Mask": "combined",
    "Method": "aCompCor",
    "Retained": false,
    "SingularValue": 42.8255390733,
    "VarianceExplained": 0.0086849493
  },
  "dropped_224": {
    "CumulativeVarianceExplained": 0.523378665,
    "Mask": "combined",
    "Method": "aCompCor",
    "Retained": false,
    "SingularValue": 42.3739119938,
    "VarianceExplained": 0.0085027367
  },
  "dropped_225": {
    "CumulativeVarianceExplained": 0.5317530394,
    "Mask": "combined",
    "Method": "aCompCor",
    "Retained": false,
    "SingularValue": 42.0528448218,
    "VarianceExplained": 0.0083743744
  },
  "dropped_226": {
    "CumulativeVarianceExplained": 0.5400361795,
    "Mask": "combined",
    "Method": "aCompCor",
    "Retained": false,
    "SingularValue": 41.8231461457,
    "VarianceExplained": 0.0082831401
  },
  "dropped_227": {
    "CumulativeVarianceExplained": 0.5482616023,
    "Mask": "combined",
    "Method": "aCompCor",
    "Retained": false,
    "SingularValue": 41.677178428,
    "VarianceExplained": 0.0082254228
  },
  "dropped_228": {
    "CumulativeVarianceExplained": 0.5563241813,
    "Mask": "combined",
    "Method": "aCompCor",
    "Retained": false,
    "SingularValue": 41.2625617819,
    "VarianceExplained": 0.008062579
  },
  "dropped_229": {
    "CumulativeVarianceExplained": 0.5641856649,
    "Mask": "combined",
    "Method": "aCompCor",
    "Retained": false,
    "SingularValue": 40.7447306575,
    "VarianceExplained": 0.0078614836
  },
  "dropped_23": {
    "CumulativeVarianceExplained": 0.8122262419,
    "Mask": "CSF",
    "Method": "aCompCor",
    "Retained": false,
    "SingularValue": 13.0673754224,
    "VarianceExplained": 0.0066517199
  },
  "dropped_230": {
    "CumulativeVarianceExplained": 0.5719827421,
    "Mask": "combined",
    "Method": "aCompCor",
    "Retained": false,
    "SingularValue": 40.5774837,
    "VarianceExplained": 0.0077970772
  },
  "dropped_231": {
    "CumulativeVarianceExplained": 0.579733818,
    "Mask": "combined",
    "Method": "aCompCor",
    "Retained": false,
    "SingularValue": 40.457606945,
    "VarianceExplained": 0.0077510759
  },
  "dropped_232": {
    "CumulativeVarianceExplained": 0.5873072848,
    "Mask": "combined",
    "Method": "aCompCor",
    "Retained": false,
    "SingularValue": 39.991395388,
    "VarianceExplained": 0.0075734668
  },
  "dropped_233": {
    "CumulativeVarianceExplained": 0.5948299865,
    "Mask": "combined",
    "Method": "aCompCor",
    "Retained": false,
    "SingularValue": 39.8571384411,
    "VarianceExplained": 0.0075227017
  },
  "dropped_234": {
    "CumulativeVarianceExplained": 0.6022797658,
    "Mask": "combined",
    "Method": "aCompCor",
    "Retained": false,
    "SingularValue": 39.663487377,
    "VarianceExplained": 0.0074497792
  },
  "dropped_235": {
    "CumulativeVarianceExplained": 0.6095961502,
    "Mask": "combined",
    "Method": "aCompCor",
    "Retained": false,
    "SingularValue": 39.3067786591,
    "VarianceExplained": 0.0073163844
  },
  "dropped_236": {
    "CumulativeVarianceExplained": 0.6168019495,
    "Mask": "combined",
    "Method": "aCompCor",
    "Retained": false,
    "SingularValue": 39.0085920806,
    "VarianceExplained": 0.0072057993
  },
  "dropped_237": {
    "CumulativeVarianceExplained": 0.6239742696,
    "Mask": "combined",
    "Method": "aCompCor",
    "Retained": false,
    "SingularValue": 38.9178667747,
    "VarianceExplained": 0.0071723201
  },
  "dropped_238": {
    "CumulativeVarianceExplained": 0.631081645,
    "Mask": "combined",
    "Method": "aCompCor",
    "Retained": false,
    "SingularValue": 38.7412671627,
    "VarianceExplained": 0.0071073754
  },
  "dropped_239": {
    "CumulativeVarianceExplained": 0.6381220542,
    "Mask": "combined",
    "Method": "aCompCor",
    "Retained": false,
    "SingularValue": 38.5583236728,
    "VarianceExplained": 0.0070404092
  },
  "dropped_24": {
    "CumulativeVarianceExplained": 0.8188507089,
    "Mask": "CSF",
    "Method": "aCompCor",
    "Retained": false,
    "SingularValue": 13.0405786984,
    "VarianceExplained": 0.006624467
  },
  "dropped_240": {
    "CumulativeVarianceExplained": 0.6450753425,
    "Mask": "combined",
    "Method": "aCompCor",
    "Retained": false,
    "SingularValue": 38.3190129775,
    "VarianceExplained": 0.0069532883
  },
  "dropped_241": {
    "CumulativeVarianceExplained": 0.6519755705,
    "Mask": "combined",
    "Method": "aCompCor",
    "Retained": false,
    "SingularValue": 38.1725272847,
    "VarianceExplained": 0.006900228
  },
  "dropped_242": {
    "CumulativeVarianceExplained": 0.6587944695,
    "Mask": "combined",
    "Method": "aCompCor",
    "Retained": false,
    "SingularValue": 37.9469019377,
    "VarianceExplained": 0.006818899
  },
  "dropped_243": {
    "CumulativeVarianceExplained": 0.6655546605,
    "Mask": "combined",
    "Method": "aCompCor",
    "Retained": false,
    "SingularValue": 37.783194878,
    "VarianceExplained": 0.006760191
  },
  "dropped_244": {
    "CumulativeVarianceExplained": 0.6721923353,
    "Mask": "combined",
    "Method": "aCompCor",
    "Retained": false,
    "SingularValue": 37.4392535132,
    "VarianceExplained": 0.0066376748
  },
  "dropped_245": {
    "CumulativeVarianceExplained": 0.6787052806,
    "Mask": "combined",
    "Method": "aCompCor",
    "Retained": false,
    "SingularValue": 37.0858221544,
    "VarianceExplained": 0.0065129453
  },
  "dropped_246": {
    "CumulativeVarianceExplained": 0.6851619451,
    "Mask": "combined",
    "Method": "aCompCor",
    "Retained": false,
    "SingularValue": 36.92523791,
    "VarianceExplained": 0.0064566644
  },
  "dropped_247": {
    "CumulativeVarianceExplained": 0.6914958734,
    "Mask": "combined",
    "Method": "aCompCor",
    "Retained": false,
    "SingularValue": 36.5725941401,
    "VarianceExplained": 0.0063339283
  },
  "dropped_248": {
    "CumulativeVarianceExplained": 0.6977224093,
    "Mask": "combined",
    "Method": "aCompCor",
    "Retained": false,
    "SingularValue": 36.2612227002,
    "VarianceExplained": 0.0062265359
  },
  "dropped_249": {
    "CumulativeVarianceExplained": 0.703911661,
    "Mask": "combined",
    "Method": "aCompCor",
    "Retained": false,
    "SingularValue": 36.1524943257,
    "VarianceExplained": 0.0061892517
  },
  "dropped_25": {
    "CumulativeVarianceExplained": 0.8251582789,
    "Mask": "CSF",
    "Method": "aCompCor",
    "Retained": false,
    "SingularValue": 12.7248430167,
    "VarianceExplained": 0.00630757
  },
  "dropped_250": {
    "CumulativeVarianceExplained": 0.7099647789,
    "Mask": "combined",
    "Method": "aCompCor",
    "Retained": false,
    "SingularValue": 35.7526931349,
    "VarianceExplained": 0.0060531179
  },
  "dropped_251": {
    "CumulativeVarianceExplained": 0.7159964539,
    "Mask": "combined",
    "Method": "aCompCor",
    "Retained": false,
    "SingularValue": 35.6893109233,
    "VarianceExplained": 0.006031675
  },
  "dropped_252": {
    "CumulativeVarianceExplained": 0.7219741142,
    "Mask": "combined",
    "Method": "aCompCor",
    "Retained": false,
    "SingularValue": 35.5291493175,
    "VarianceExplained": 0.0059776603
  },
  "dropped_253": {
    "CumulativeVarianceExplained": 0.7278967665,
    "Mask": "combined",
    "Method": "aCompCor",
    "Retained": false,
    "SingularValue": 35.3652974187,
    "VarianceExplained": 0.0059226523
  },
  "dropped_254": {
    "CumulativeVarianceExplained": 0.7337935037,
    "Mask": "combined",
    "Method": "aCompCor",
    "Retained": false,
    "SingularValue": 35.2878403311,
    "VarianceExplained": 0.0058967372
  },
  "dropped_255": {
    "CumulativeVarianceExplained": 0.7396157629,
    "Mask": "combined",
    "Method": "aCompCor",
    "Retained": false,
    "SingularValue": 35.0642830895,
    "VarianceExplained": 0.0058222592
  },
  "dropped_256": {
    "CumulativeVarianceExplained": 0.7453686759,
    "Mask": "combined",
    "Method": "aCompCor",
    "Retained": false,
    "SingularValue": 34.8548403001,
    "VarianceExplained": 0.005752913
  },
  "dropped_257": {
    "CumulativeVarianceExplained": 0.7510613838,
    "Mask": "combined",
    "Method": "aCompCor",
    "Retained": false,
    "SingularValue": 34.6719802596,
    "VarianceExplained": 0.0056927079
  },
  "dropped_258": {
    "CumulativeVarianceExplained": 0.7567234729,
    "Mask": "combined",
    "Method": "aCompCor",
    "Retained": false,
    "SingularValue": 34.5786109109,
    "VarianceExplained": 0.0056620891
  },
  "dropped_259": {
    "CumulativeVarianceExplained": 0.7623170713,
    "Mask": "combined",
    "Method": "aCompCor",
    "Retained": false,
    "SingularValue": 34.3688371073,
    "VarianceExplained": 0.0055935984
  },
  "dropped_26": {
    "CumulativeVarianceExplained": 0.8311469501,
    "Mask": "CSF",
    "Method": "aCompCor",
    "Retained": false,
    "SingularValue": 12.3989991543,
    "VarianceExplained": 0.0059886713
  },
  "dropped_260": {
    "CumulativeVarianceExplained": 0.7678357912,
    "Mask": "combined",
    "Method": "aCompCor",
    "Retained": false,
    "SingularValue": 34.1380233829,
    "VarianceExplained": 0.0055187199
  },
  "dropped_261": {
    "CumulativeVarianceExplained": 0.7733043461,
    "Mask": "combined",
    "Method": "aCompCor",
    "Retained": false,
    "SingularValue": 33.9825121003,
    "VarianceExplained": 0.0054685548
  },
  "dropped_262": {
    "CumulativeVarianceExplained": 0.7786919005,
    "Mask": "combined",
    "Method": "aCompCor",
    "Retained": false,
    "SingularValue": 33.7298983228,
    "VarianceExplained": 0.0053875545
  },
  "dropped_263": {
    "CumulativeVarianceExplained": 0.7839979938,
    "Mask": "combined",
    "Method": "aCompCor",
    "Retained": false,
    "SingularValue": 33.4739246566,
    "VarianceExplained": 0.0053060933
  },
  "dropped_264": {
    "CumulativeVarianceExplained": 0.7892815895,
    "Mask": "combined",
    "Method": "aCompCor",
    "Retained": false,
    "SingularValue": 33.4028854074,
    "VarianceExplained": 0.0052835957
  },
  "dropped_265": {
    "CumulativeVarianceExplained": 0.7944959613,
    "Mask": "combined",
    "Method": "aCompCor",
    "Retained": false,
    "SingularValue": 33.1833473108,
    "VarianceExplained": 0.0052143718
  },
  "dropped_266": {
    "CumulativeVarianceExplained": 0.7996668874,
    "Mask": "combined",
    "Method": "aCompCor",
    "Retained": false,
    "SingularValue": 33.0448176943,
    "VarianceExplained": 0.0051709261
  },
  "dropped_267": {
    "CumulativeVarianceExplained": 0.8047766289,
    "Mask": "combined",
    "Method": "aCompCor",
    "Retained": false,
    "SingularValue": 32.8487356545,
    "VarianceExplained": 0.0051097415
  },
  "dropped_268": {
    "CumulativeVarianceExplained": 0.8098511823,
    "Mask": "combined",
    "Method": "aCompCor",
    "Retained": false,
    "SingularValue": 32.7354344202,
    "VarianceExplained": 0.0050745534
  },
  "dropped_269": {
    "CumulativeVarianceExplained": 0.814828727,
    "Mask": "combined",
    "Method": "aCompCor",
    "Retained": false,
    "SingularValue": 32.421027996,
    "VarianceExplained": 0.0049775447
  },
  "dropped_27": {
    "CumulativeVarianceExplained": 0.8370053716,
    "Mask": "CSF",
    "Method": "aCompCor",
    "Retained": false,
    "SingularValue": 12.2634227099,
    "VarianceExplained": 0.0058584214
  },
  "dropped_270": {
    "CumulativeVarianceExplained": 0.8197602167,
    "Mask": "combined",
    "Method": "aCompCor",
    "Retained": false,
    "SingularValue": 32.2706906079,
    "VarianceExplained": 0.0049314897
  },
  "dropped_271": {
    "CumulativeVarianceExplained": 0.8246315868,
    "Mask": "combined",
    "Method": "aCompCor",
    "Retained": false,
    "SingularValue": 32.0733820072,
    "VarianceExplained": 0.0048713701
  },
  "dropped_272": {
    "CumulativeVarianceExplained": 0.8294075589,
    "Mask": "combined",
    "Method": "aCompCor",
    "Retained": false,
    "SingularValue": 31.7577763435,
    "VarianceExplained": 0.0047759721
  },
  "dropped_273": {
    "CumulativeVarianceExplained": 0.8341662361,
    "Mask": "combined",
    "Method": "aCompCor",
    "Retained": false,
    "SingularValue": 31.7002229823,
    "VarianceExplained": 0.0047586772
  },
  "dropped_274": {
    "CumulativeVarianceExplained": 0.8388752166,
    "Mask": "combined",
    "Method": "aCompCor",
    "Retained": false,
    "SingularValue": 31.5342596719,
    "VarianceExplained": 0.0047089805
  },
  "dropped_275": {
    "CumulativeVarianceExplained": 0.8435080477,
    "Mask": "combined",
    "Method": "aCompCor",
    "Retained": false,
    "SingularValue": 31.278248972,
    "VarianceExplained": 0.0046328312
  },
  "dropped_276": {
    "CumulativeVarianceExplained": 0.848139454,
    "Mask": "combined",
    "Method": "aCompCor",
    "Retained": false,
    "SingularValue": 31.2734384748,
    "VarianceExplained": 0.0046314063
  },
  "dropped_277": {
    "CumulativeVarianceExplained": 0.852679852,
    "Mask": "combined",
    "Method": "aCompCor",
    "Retained": false,
    "SingularValue": 30.9646486832,
    "VarianceExplained": 0.004540398
  },
  "dropped_278": {
    "CumulativeVarianceExplained": 0.8572151688,
    "Mask": "combined",
    "Method": "aCompCor",
    "Retained": false,
    "SingularValue": 30.9473173026,
    "VarianceExplained": 0.0045353168
  },
  "dropped_279": {
    "CumulativeVarianceExplained": 0.8616692857,
    "Mask": "combined",
    "Method": "aCompCor",
    "Retained": false,
    "SingularValue": 30.6690273825,
    "VarianceExplained": 0.004454117
  },
  "dropped_28": {
    "CumulativeVarianceExplained": 0.8425352249,
    "Mask": "CSF",
    "Method": "aCompCor",
    "Retained": false,
    "SingularValue": 11.9145652454,
    "VarianceExplained": 0.0055298533
  },
  "dropped_280": {
    "CumulativeVarianceExplained": 0.8660638811,
    "Mask": "combined",
    "Method": "aCompCor",
    "Retained": false,
    "SingularValue": 30.4634188419,
    "VarianceExplained": 0.0043945954
  },
  "dropped_281": {
    "CumulativeVarianceExplained": 0.8703774932,
    "Mask": "combined",
    "Method": "aCompCor",
    "Retained": false,
    "SingularValue": 30.1814248161,
    "VarianceExplained": 0.0043136121
  },
  "dropped_282": {
    "CumulativeVarianceExplained": 0.8746168238,
    "Mask": "combined",
    "Method": "aCompCor",
    "Retained": false,
    "SingularValue": 29.9204305496,
    "VarianceExplained": 0.0042393306
  },
  "dropped_283": {
    "CumulativeVarianceExplained": 0.878841445,
    "Mask": "combined",
    "Method": "aCompCor",
    "Retained": false,
    "SingularValue": 29.8684772746,
    "VarianceExplained": 0.0042246212
  },
  "dropped_284": {
    "CumulativeVarianceExplained": 0.883013122,
    "Mask": "combined",
    "Method": "aCompCor",
    "Retained": false,
    "SingularValue": 29.6807267413,
    "VarianceExplained": 0.004171677
  },
  "dropped_285": {
    "CumulativeVarianceExplained": 0.8871525287,
    "Mask": "combined",
    "Method": "aCompCor",
    "Retained": false,
    "SingularValue": 29.5657055368,
    "VarianceExplained": 0.0041394068
  },
  "dropped_286": {
    "CumulativeVarianceExplained": 0.8912554627,
    "Mask": "combined",
    "Method": "aCompCor",
    "Retained": false,
    "SingularValue": 29.435163726,
    "VarianceExplained": 0.0041029339
  },
  "dropped_287": {
    "CumulativeVarianceExplained": 0.8952959594,
    "Mask": "combined",
    "Method": "aCompCor",
    "Retained": false,
    "SingularValue": 29.2103373915,
    "VarianceExplained": 0.0040404967
  },
  "dropped_288": {
    "CumulativeVarianceExplained": 0.8992858868,
    "Mask": "combined",
    "Method": "aCompCor",
    "Retained": false,
    "SingularValue": 29.0269692171,
    "VarianceExplained": 0.0039899274
  },
  "dropped_289": {
    "CumulativeVarianceExplained": 0.9032548271,
    "Mask": "combined",
    "Method": "aCompCor",
    "Retained": false,
    "SingularValue": 28.9505272571,
    "VarianceExplained": 0.0039689403
  },
  "dropped_29": {
    "CumulativeVarianceExplained": 0.8479458355,
    "Mask": "CSF",
    "Method": "aCompCor",
    "Retained": false,
    "SingularValue": 11.7854055304,
    "VarianceExplained": 0.0054106106
  },
  "dropped_290": {
    "CumulativeVarianceExplained": 0.9071424645,
    "Mask": "combined",
    "Method": "aCompCor",
    "Retained": false,
    "SingularValue": 28.6524704344,
    "VarianceExplained": 0.0038876374
  },
  "dropped_291": {
    "CumulativeVarianceExplained": 0.911012719,
    "Mask": "combined",
    "Method": "aCompCor",
    "Retained": false,
    "SingularValue": 28.5883412521,
    "VarianceExplained": 0.0038702545
  },
  "dropped_292": {
    "CumulativeVarianceExplained": 0.9148022857,
    "Mask": "combined",
    "Method": "aCompCor",
    "Retained": false,
    "SingularValue": 28.2887639484,
    "VarianceExplained": 0.0037895667
  },
  "dropped_293": {
    "CumulativeVarianceExplained": 0.918550725,
    "Mask": "combined",
    "Method": "aCompCor",
    "Retained": false,
    "SingularValue": 28.1348390529,
    "VarianceExplained": 0.0037484393
  },
  "dropped_294": {
    "CumulativeVarianceExplained": 0.9222633795,
    "Mask": "combined",
    "Method": "aCompCor",
    "Retained": false,
    "SingularValue": 28.0002214265,
    "VarianceExplained": 0.0037126546
  },
  "dropped_295": {
    "CumulativeVarianceExplained": 0.9259559959,
    "Mask": "combined",
    "Method": "aCompCor",
    "Retained": false,
    "SingularValue": 27.9245567615,
    "VarianceExplained": 0.0036926163
  },
  "dropped_296": {
    "CumulativeVarianceExplained": 0.9295562274,
    "Mask": "combined",
    "Method": "aCompCor",
    "Retained": false,
    "SingularValue": 27.5730248316,
    "VarianceExplained": 0.0036002316
  },
  "dropped_297": {
    "CumulativeVarianceExplained": 0.9331455449,
    "Mask": "combined",
    "Method": "aCompCor",
    "Retained": false,
    "SingularValue": 27.531199322,
    "VarianceExplained": 0.0035893175
  },
  "dropped_298": {
    "CumulativeVarianceExplained": 0.9366861757,
    "Mask": "combined",
    "Method": "aCompCor",
    "Retained": false,
    "SingularValue": 27.343840648,
    "VarianceExplained": 0.0035406308
  },
  "dropped_299": {
    "CumulativeVarianceExplained": 0.9401655765,
    "Mask": "combined",
    "Method": "aCompCor",
    "Retained": false,
    "SingularValue": 27.1063740677,
    "VarianceExplained": 0.0034794008
  },
  "dropped_3": {
    "CumulativeVarianceExplained": 0.6034756291,
    "Mask": "CSF",
    "Method": "aCompCor",
    "Retained": false,
    "SingularValue": 21.9745405743,
    "VarianceExplained": 0.0188103476
  },
  "dropped_30": {
    "CumulativeVarianceExplained": 0.8531944893,
    "Mask": "CSF",
    "Method": "aCompCor",
    "Retained": false,
    "SingularValue": 11.6076781828,
    "VarianceExplained": 0.0052486538
  },
  "dropped_300": {
    "CumulativeVarianceExplained": 0.943618914,
    "Mask": "combined",
    "Method": "aCompCor",
    "Retained": false,
    "SingularValue": 27.0046597321,
    "VarianceExplained": 0.0034533375
  },
  "dropped_301": {
    "CumulativeVarianceExplained": 0.9469952616,
    "Mask": "combined",
    "Method": "aCompCor",
    "Retained": false,
    "SingularValue": 26.7019372091,
    "VarianceExplained": 0.0033763476
  },
  "dropped_302": {
    "CumulativeVarianceExplained": 0.9503255241,
    "Mask": "combined",
    "Method": "aCompCor",
    "Retained": false,
    "SingularValue": 26.5190785028,
    "VarianceExplained": 0.0033302625
  },
  "dropped_303": {
    "CumulativeVarianceExplained": 0.953638564,
    "Mask": "combined",
    "Method": "aCompCor",
    "Retained": false,
    "SingularValue": 26.4504171043,
    "VarianceExplained": 0.0033130399
  },
  "dropped_304": {
    "CumulativeVarianceExplained": 0.9568967995,
    "Mask": "combined",
    "Method": "aCompCor",
    "Retained": false,
    "SingularValue": 26.2307333078,
    "VarianceExplained": 0.0032582355
  },
  "dropped_305": {
    "CumulativeVarianceExplained": 0.9601044495,
    "Mask": "combined",
    "Method": "aCompCor",
    "Retained": false,
    "SingularValue": 26.0263148516,
    "VarianceExplained": 0.00320765
  },
  "dropped_306": {
    "CumulativeVarianceExplained": 0.9632988037,
    "Mask": "combined",
    "Method": "aCompCor",
    "Retained": false,
    "SingularValue": 25.9723191488,
    "VarianceExplained": 0.0031943542
  },
  "dropped_307": {
    "CumulativeVarianceExplained": 0.9664709337,
    "Mask": "combined",
    "Method": "aCompCor",
    "Retained": false,
    "SingularValue": 25.8818122598,
    "VarianceExplained": 0.00317213
  },
  "dropped_308": {
    "CumulativeVarianceExplained": 0.9696005636,
    "Mask": "combined",
    "Method": "aCompCor",
    "Retained": false,
    "SingularValue": 25.7078458597,
    "VarianceExplained": 0.0031296299
  },
  "dropped_309": {
    "CumulativeVarianceExplained": 0.9726602377,
    "Mask": "combined",
    "Method": "aCompCor",
    "Retained": false,
    "SingularValue": 25.4189014606,
    "VarianceExplained": 0.0030596741
  },
  "dropped_31": {
    "CumulativeVarianceExplained": 0.8584016319,
    "Mask": "CSF",
    "Method": "aCompCor",
    "Retained": false,
    "SingularValue": 11.5616848928,
    "VarianceExplained": 0.0052071426
  },
  "dropped_310": {
    "CumulativeVarianceExplained": 0.97567073,
    "Mask": "combined",
    "Method": "aCompCor",
    "Retained": false,
    "SingularValue": 25.2137798271,
    "VarianceExplained": 0.0030104923
  },
  "dropped_311": {
    "CumulativeVarianceExplained": 0.9786125668,
    "Mask": "combined",
    "Method": "aCompCor",
    "Retained": false,
    "SingularValue": 24.9246164894,
    "VarianceExplained": 0.0029418368
  },
  "dropped_312": {
    "CumulativeVarianceExplained": 0.9814974116,
    "Mask": "combined",
    "Method": "aCompCor",
    "Retained": false,
    "SingularValue": 24.6820040188,
    "VarianceExplained": 0.0028848448
  },
  "dropped_313": {
    "CumulativeVarianceExplained": 0.9843055704,
    "Mask": "combined",
    "Method": "aCompCor",
    "Retained": false,
    "SingularValue": 24.3517416538,
    "VarianceExplained": 0.0028081588
  },
  "dropped_314": {
    "CumulativeVarianceExplained": 0.9870914144,
    "Mask": "combined",
    "Method": "aCompCor",
    "Retained": false,
    "SingularValue": 24.2547943529,
    "VarianceExplained": 0.0027858441
  },
  "dropped_315": {
    "CumulativeVarianceExplained": 0.9898088868,
    "Mask": "combined",
    "Method": "aCompCor",
    "Retained": false,
    "SingularValue": 23.9553082702,
    "VarianceExplained": 0.0027174724
  },
  "dropped_316": {
    "CumulativeVarianceExplained": 0.9924666508,
    "Mask": "combined",
    "Method": "aCompCor",
    "Retained": false,
    "SingularValue": 23.6906732484,
    "VarianceExplained": 0.002657764
  },
  "dropped_317": {
    "CumulativeVarianceExplained": 0.9950702364,
    "Mask": "combined",
    "Method": "aCompCor",
    "Retained": false,
    "SingularValue": 23.4479631539,
    "VarianceExplained": 0.0026035856
  },
  "dropped_318": {
    "CumulativeVarianceExplained": 0.9975700536,
    "Mask": "combined",
    "Method": "aCompCor",
    "Retained": false,
    "SingularValue": 22.9759416428,
    "VarianceExplained": 0.0024998172
  },
  "dropped_319": {
    "CumulativeVarianceExplained": 1.0,
    "Mask": "combined",
    "Method": "aCompCor",
    "Retained": false,
    "SingularValue": 22.6525732423,
    "VarianceExplained": 0.0024299464
  },
  "dropped_32": {
    "CumulativeVarianceExplained": 0.8634738656,
    "Mask": "CSF",
    "Method": "aCompCor",
    "Retained": false,
    "SingularValue": 11.4109295168,
    "VarianceExplained": 0.0050722337
  },
  "dropped_320": {
    "CumulativeVarianceExplained": 1.0,
    "Mask": "combined",
    "Method": "aCompCor",
    "Retained": false,
    "SingularValue": 0.0,
    "VarianceExplained": 0.0
  },
  "dropped_321": {
    "CumulativeVarianceExplained": 1.0,
    "Mask": "combined",
    "Method": "aCompCor",
    "Retained": false,
    "SingularValue": 0.0,
    "VarianceExplained": 0.0
  },
  "dropped_322": {
    "CumulativeVarianceExplained": 1.0,
    "Mask": "combined",
    "Method": "aCompCor",
    "Retained": false,
    "SingularValue": 0.0,
    "VarianceExplained": 0.0
  },
  "dropped_323": {
    "CumulativeVarianceExplained": 1.0,
    "Mask": "combined",
    "Method": "aCompCor",
    "Retained": false,
    "SingularValue": 0.0,
    "VarianceExplained": 0.0
  },
  "dropped_33": {
    "CumulativeVarianceExplained": 0.8682761525,
    "Mask": "CSF",
    "Method": "aCompCor",
    "Retained": false,
    "SingularValue": 11.103130486,
    "VarianceExplained": 0.0048022869
  },
  "dropped_34": {
    "CumulativeVarianceExplained": 0.87301792,
    "Mask": "CSF",
    "Method": "aCompCor",
    "Retained": false,
    "SingularValue": 11.032946743,
    "VarianceExplained": 0.0047417675
  },
  "dropped_35": {
    "CumulativeVarianceExplained": 0.877637592,
    "Mask": "CSF",
    "Method": "aCompCor",
    "Retained": false,
    "SingularValue": 10.8899769567,
    "VarianceExplained": 0.0046196719
  },
  "dropped_36": {
    "CumulativeVarianceExplained": 0.8821526692,
    "Mask": "CSF",
    "Method": "aCompCor",
    "Retained": false,
    "SingularValue": 10.7659903561,
    "VarianceExplained": 0.0045150773
  },
  "dropped_37": {
    "CumulativeVarianceExplained": 0.886468908,
    "Mask": "CSF",
    "Method": "aCompCor",
    "Retained": false,
    "SingularValue": 10.5262606865,
    "VarianceExplained": 0.0043162387
  },
  "dropped_38": {
    "CumulativeVarianceExplained": 0.8906105068,
    "Mask": "CSF",
    "Method": "aCompCor",
    "Retained": false,
    "SingularValue": 10.3111097097,
    "VarianceExplained": 0.0041415988
  },
  "dropped_39": {
    "CumulativeVarianceExplained": 0.8944192823,
    "Mask": "CSF",
    "Method": "aCompCor",
    "Retained": false,
    "SingularValue": 9.8881280791,
    "VarianceExplained": 0.0038087755
  },
  "dropped_4": {
    "CumulativeVarianceExplained": 0.6203048012,
    "Mask": "CSF",
    "Method": "aCompCor",
    "Retained": false,
    "SingularValue": 20.7851311713,
    "VarianceExplained": 0.0168291721
  },
  "dropped_40": {
    "CumulativeVarianceExplained": 0.8981911361,
    "Mask": "CSF",
    "Method": "aCompCor",
    "Retained": false,
    "SingularValue": 9.8400842302,
    "VarianceExplained": 0.0037718538
  },
  "dropped_41": {
    "CumulativeVarianceExplained": 0.901892866,
    "Mask": "CSF",
    "Method": "aCompCor",
    "Retained": false,
    "SingularValue": 9.7481849044,
    "VarianceExplained": 0.0037017299
  },
  "dropped_42": {
    "CumulativeVarianceExplained": 0.9054596271,
    "Mask": "CSF",
    "Method": "aCompCor",
    "Retained": false,
    "SingularValue": 9.5688204919,
    "VarianceExplained": 0.0035667612
  },
  "dropped_43": {
    "CumulativeVarianceExplained": 0.9089755325,
    "Mask": "CSF",
    "Method": "aCompCor",
    "Retained": false,
    "SingularValue": 9.5003582011,
    "VarianceExplained": 0.0035159053
  },
  "dropped_44": {
    "CumulativeVarianceExplained": 0.9123185142,
    "Mask": "CSF",
    "Method": "aCompCor",
    "Retained": false,
    "SingularValue": 9.2637833846,
    "VarianceExplained": 0.0033429817
  },
  "dropped_45": {
    "CumulativeVarianceExplained": 0.9156083099,
    "Mask": "CSF",
    "Method": "aCompCor",
    "Retained": false,
    "SingularValue": 9.1897957748,
    "VarianceExplained": 0.0032897957
  },
  "dropped_46": {
    "CumulativeVarianceExplained": 0.9187980101,
    "Mask": "CSF",
    "Method": "aCompCor",
    "Retained": false,
    "SingularValue": 9.0489112014,
    "VarianceExplained": 0.0031897002
  },
  "dropped_47": {
    "CumulativeVarianceExplained": 0.9218091731,
    "Mask": "CSF",
    "Method": "aCompCor",
    "Retained": false,
    "SingularValue": 8.7920170983,
    "VarianceExplained": 0.003011163
  },
  "dropped_48": {
    "CumulativeVarianceExplained": 0.9247539711,
    "Mask": "CSF",
    "Method": "aCompCor",
    "Retained": false,
    "SingularValue": 8.6945908746,
    "VarianceExplained": 0.002944798
  },
  "dropped_49": {
    "CumulativeVarianceExplained": 0.9276801807,
    "Mask": "CSF",
    "Method": "aCompCor",
    "Retained": false,
    "SingularValue": 8.6671060025,
    "VarianceExplained": 0.0029262096
  },
  "dropped_5": {
    "CumulativeVarianceExplained": 0.6361879236,
    "Mask": "CSF",
    "Method": "aCompCor",
    "Retained": false,
    "SingularValue": 20.1924647983,
    "VarianceExplained": 0.0158831224
  },
  "dropped_50": {
    "CumulativeVarianceExplained": 0.930580011,
    "Mask": "CSF",
    "Method": "aCompCor",
    "Retained": false,
    "SingularValue": 8.6279512698,
    "VarianceExplained": 0.0028998303
  },
  "dropped_51": {
    "CumulativeVarianceExplained": 0.9333823482,
    "Mask": "CSF",
    "Method": "aCompCor",
    "Retained": false,
    "SingularValue": 8.4816742528,
    "VarianceExplained": 0.0028023372
  },
  "dropped_52": {
    "CumulativeVarianceExplained": 0.9361218488,
    "Mask": "CSF",
    "Method": "aCompCor",
    "Retained": false,
    "SingularValue": 8.3860432241,
    "VarianceExplained": 0.0027395006
  },
  "dropped_53": {
    "CumulativeVarianceExplained": 0.9387480335,
    "Mask": "CSF",
    "Method": "aCompCor",
    "Retained": false,
    "SingularValue": 8.2107725594,
    "VarianceExplained": 0.0026261846
  },
  "dropped_54": {
    "CumulativeVarianceExplained": 0.9412574158,
    "Mask": "CSF",
    "Method": "aCompCor",
    "Retained": false,
    "SingularValue": 8.0261044948,
    "VarianceExplained": 0.0025093823
  },
  "dropped_55": {
    "CumulativeVarianceExplained": 0.9437572886,
    "Mask": "CSF",
    "Method": "aCompCor",
    "Retained": false,
    "SingularValue": 8.0108822976,
    "VarianceExplained": 0.0024998728
  },
  "dropped_56": {
    "CumulativeVarianceExplained": 0.9461927272,
    "Mask": "CSF",
    "Method": "aCompCor",
    "Retained": false,
    "SingularValue": 7.9069680688,
    "VarianceExplained": 0.0024354386
  },
  "dropped_57": {
    "CumulativeVarianceExplained": 0.9484953193,
    "Mask": "CSF",
    "Method": "aCompCor",
    "Retained": false,
    "SingularValue": 7.6882925687,
    "VarianceExplained": 0.0023025921
  },
  "dropped_58": {
    "CumulativeVarianceExplained": 0.9507232055,
    "Mask": "CSF",
    "Method": "aCompCor",
    "Retained": false,
    "SingularValue": 7.5625435469,
    "VarianceExplained": 0.0022278861
  },
  "dropped_59": {
    "CumulativeVarianceExplained": 0.9529038316,
    "Mask": "CSF",
    "Method": "aCompCor",
    "Retained": false,
    "SingularValue": 7.4819016569,
    "VarianceExplained": 0.0021806261
  },
  "dropped_6": {
    "CumulativeVarianceExplained": 0.6513799462,
    "Mask": "CSF",
    "Method": "aCompCor",
    "Retained": false,
    "SingularValue": 19.7482761792,
    "VarianceExplained": 0.0151920226
  },
  "dropped_60": {
    "CumulativeVarianceExplained": 0.9550247647,
    "Mask": "CSF",
    "Method": "aCompCor",
    "Retained": false,
    "SingularValue": 7.378785398,
    "VarianceExplained": 0.0021209331
  },
  "dropped_61": {
    "CumulativeVarianceExplained": 0.9570996121,
    "Mask": "CSF",
    "Method": "aCompCor",
    "Retained": false,
    "SingularValue": 7.2981785154,
    "VarianceExplained": 0.0020748475
  },
  "dropped_62": {
    "CumulativeVarianceExplained": 0.9590234305,
    "Mask": "CSF",
    "Method": "aCompCor",
    "Retained": false,
    "SingularValue": 7.0275416501,
    "VarianceExplained": 0.0019238184
  },
  "dropped_63": {
    "CumulativeVarianceExplained": 0.9608695678,
    "Mask": "CSF",
    "Method": "aCompCor",
    "Retained": false,
    "SingularValue": 6.8841985804,
    "VarianceExplained": 0.0018461373
  },
  "dropped_64": {
    "CumulativeVarianceExplained": 0.9626640883,
    "Mask": "CSF",
    "Method": "aCompCor",
    "Retained": false,
    "SingularValue": 6.7872774271,
    "VarianceExplained": 0.0017945205
  },
  "dropped_65": {
    "CumulativeVarianceExplained": 0.9644142672,
    "Mask": "CSF",
    "Method": "aCompCor",
    "Retained": false,
    "SingularValue": 6.7028980591,
    "VarianceExplained": 0.0017501789
  },
  "dropped_66": {
    "CumulativeVarianceExplained": 0.9660894283,
    "Mask": "CSF",
    "Method": "aCompCor",
    "Retained": false,
    "SingularValue": 6.5576718897,
    "VarianceExplained": 0.0016751611
  },
  "dropped_67": {
    "CumulativeVarianceExplained": 0.9677031246,
    "Mask": "CSF",
    "Method": "aCompCor",
    "Retained": false,
    "SingularValue": 6.4362409669,
    "VarianceExplained": 0.0016136963
  },
  "dropped_68": {
    "CumulativeVarianceExplained": 0.9692426703,
    "Mask": "CSF",
    "Method": "aCompCor",
    "Retained": false,
    "SingularValue": 6.2866268728,
    "VarianceExplained": 0.0015395457
  },
  "dropped_69": {
    "CumulativeVarianceExplained": 0.970721257,
    "Mask": "CSF",
    "Method": "aCompCor",
    "Retained": false,
    "SingularValue": 6.1609090298,
    "VarianceExplained": 0.0014785867
  },
  "dropped_7": {
    "CumulativeVarianceExplained": 0.6647314377,
    "Mask": "CSF",
    "Method": "aCompCor",
    "Retained": false,
    "SingularValue": 18.5134043034,
    "VarianceExplained": 0.0133514915
  },
  "dropped_70": {
    "CumulativeVarianceExplained": 0.9721775066,
    "Mask": "CSF",
    "Method": "aCompCor",
    "Retained": false,
    "SingularValue": 6.1141953115,
    "VarianceExplained": 0.0014562496
  },
  "dropped_71": {
    "CumulativeVarianceExplained": 0.973594555,
    "Mask": "CSF",
    "Method": "aCompCor",
    "Retained": false,
    "SingularValue": 6.0313389629,
    "VarianceExplained": 0.0014170484
  },
  "dropped_72": {
    "CumulativeVarianceExplained": 0.9748773321,
    "Mask": "CSF",
    "Method": "aCompCor",
    "Retained": false,
    "SingularValue": 5.7384816226,
    "VarianceExplained": 0.0012827771
  },
  "dropped_73": {
    "CumulativeVarianceExplained": 0.9761073949,
    "Mask": "CSF",
    "Method": "aCompCor",
    "Retained": false,
    "SingularValue": 5.6193362328,
    "VarianceExplained": 0.0012300627
  },
  "dropped_74": {
    "CumulativeVarianceExplained": 0.9773233399,
    "Mask": "CSF",
    "Method": "aCompCor",
    "Retained": false,
    "SingularValue": 5.5869960737,
    "VarianceExplained": 0.001215945
  },
  "dropped_75": {
    "CumulativeVarianceExplained": 0.978473054,
    "Mask": "CSF",
    "Method": "aCompCor",
    "Retained": false,
    "SingularValue": 5.4327074988,
    "VarianceExplained": 0.0011497141
  },
  "dropped_76": {
    "CumulativeVarianceExplained": 0.9796008689,
    "Mask": "CSF",
    "Method": "aCompCor",
    "Retained": false,
    "SingularValue": 5.3807188609,
    "VarianceExplained": 0.0011278149
  },
  "dropped_77": {
    "CumulativeVarianceExplained": 0.9806967753,
    "Mask": "CSF",
    "Method": "aCompCor",
    "Retained": false,
    "SingularValue": 5.3040564208,
    "VarianceExplained": 0.0010959065
  },
  "dropped_78": {
    "CumulativeVarianceExplained": 0.9817472367,
    "Mask": "CSF",
    "Method": "aCompCor",
    "Retained": false,
    "SingularValue": 5.1929175897,
    "VarianceExplained": 0.0010504613
  },
  "dropped_79": {
    "CumulativeVarianceExplained": 0.9827451662,
    "Mask": "CSF",
    "Method": "aCompCor",
    "Retained": false,
    "SingularValue": 5.0614079418,
    "VarianceExplained": 0.0009979296
  },
  "dropped_8": {
    "CumulativeVarianceExplained": 0.677553902,
    "Mask": "CSF",
    "Method": "aCompCor",
    "Retained": false,
    "SingularValue": 18.1429182168,
    "VarianceExplained": 0.0128224643
  },
  "dropped_80": {
    "CumulativeVarianceExplained": 0.9837319091,
    "Mask": "CSF",
    "Method": "aCompCor",
    "Retained": false,
    "SingularValue": 5.0329589027,
    "VarianceExplained": 0.0009867428
  },
  "dropped_81": {
    "CumulativeVarianceExplained": 0.9846706434,
    "Mask": "CSF",
    "Method": "aCompCor",
    "Retained": false,
    "SingularValue": 4.9089968199,
    "VarianceExplained": 0.0009387344
  },
  "dropped_82": {
    "CumulativeVarianceExplained": 0.9855580662,
    "Mask": "CSF",
    "Method": "aCompCor",
    "Retained": false,
    "SingularValue": 4.7729478231,
    "VarianceExplained": 0.0008874228
  },
  "dropped_83": {
    "CumulativeVarianceExplained": 0.9864194717,
    "Mask": "CSF",
    "Method": "aCompCor",
    "Retained": false,
    "SingularValue": 4.7024611197,
    "VarianceExplained": 0.0008614055
  },
  "dropped_84": {
    "CumulativeVarianceExplained": 0.9872467119,
    "Mask": "CSF",
    "Method": "aCompCor",
    "Retained": false,
    "SingularValue": 4.6082623506,
    "VarianceExplained": 0.0008272402
  },
  "dropped_85": {
    "CumulativeVarianceExplained": 0.9880170388,
    "Mask": "CSF",
    "Method": "aCompCor",
    "Retained": false,
    "SingularValue": 4.4469159784,
    "VarianceExplained": 0.0007703269
  },
  "dropped_86": {
    "CumulativeVarianceExplained": 0.9887671087,
    "Mask": "CSF",
    "Method": "aCompCor",
    "Retained": false,
    "SingularValue": 4.3880569689,
    "VarianceExplained": 0.0007500699
  },
  "dropped_87": {
    "CumulativeVarianceExplained": 0.9894943711,
    "Mask": "CSF",
    "Method": "aCompCor",
    "Retained": false,
    "SingularValue": 4.3208279774,
    "VarianceExplained": 0.0007272625
  },
  "dropped_88": {
    "CumulativeVarianceExplained": 0.9902204417,
    "Mask": "CSF",
    "Method": "aCompCor",
    "Retained": false,
    "SingularValue": 4.3172858956,
    "VarianceExplained": 0.0007260706
  },
  "dropped_89": {
    "CumulativeVarianceExplained": 0.9909158803,
    "Mask": "CSF",
    "Method": "aCompCor",
    "Retained": false,
    "SingularValue": 4.2252342841,
    "VarianceExplained": 0.0006954386
  },
  "dropped_9": {
    "CumulativeVarianceExplained": 0.6895018261,
    "Mask": "CSF",
    "Method": "aCompCor",
    "Retained": false,
    "SingularValue": 17.5132851842,
    "VarianceExplained": 0.011947924
  },
  "dropped_90": {
    "CumulativeVarianceExplained": 0.9915630963,
    "Mask": "CSF",
    "Method": "aCompCor",
    "Retained": false,
    "SingularValue": 4.0761112414,
    "VarianceExplained": 0.000647216
  },
  "dropped_91": {
    "CumulativeVarianceExplained": 0.992151895,
    "Mask": "CSF",
    "Method": "aCompCor",
    "Retained": false,
    "SingularValue": 3.887807819,
    "VarianceExplained": 0.0005887986
  },
  "dropped_92": {
    "CumulativeVarianceExplained": 0.9927372709,
    "Mask": "CSF",
    "Method": "aCompCor",
    "Retained": false,
    "SingularValue": 3.8764913807,
    "VarianceExplained": 0.0005853759
  },
  "dropped_93": {
    "CumulativeVarianceExplained": 0.9932708187,
    "Mask": "CSF",
    "Method": "aCompCor",
    "Retained": false,
    "SingularValue": 3.7009060943,
    "VarianceExplained": 0.0005335478
  },
  "dropped_94": {
    "CumulativeVarianceExplained": 0.9937669489,
    "Mask": "CSF",
    "Method": "aCompCor",
    "Retained": false,
    "SingularValue": 3.5687752523,
    "VarianceExplained": 0.0004961301
  },
  "dropped_95": {
    "CumulativeVarianceExplained": 0.9942472574,
    "Mask": "CSF",
    "Method": "aCompCor",
    "Retained": false,
    "SingularValue": 3.5114102395,
    "VarianceExplained": 0.0004803086
  },
  "dropped_96": {
    "CumulativeVarianceExplained": 0.9947162707,
    "Mask": "CSF",
    "Method": "aCompCor",
    "Retained": false,
    "SingularValue": 3.4698761434,
    "VarianceExplained": 0.0004690133
  },
  "dropped_97": {
    "CumulativeVarianceExplained": 0.9951591271,
    "Mask": "CSF",
    "Method": "aCompCor",
    "Retained": false,
    "SingularValue": 3.3717304203,
    "VarianceExplained": 0.0004428564
  },
  "dropped_98": {
    "CumulativeVarianceExplained": 0.9955899087,
    "Mask": "CSF",
    "Method": "aCompCor",
    "Retained": false,
    "SingularValue": 3.3254465934,
    "VarianceExplained": 0.0004307816
  },
  "dropped_99": {
    "CumulativeVarianceExplained": 0.9959890983,
    "Mask": "CSF",
    "Method": "aCompCor",
    "Retained": false,
    "SingularValue": 3.2011865333,
    "VarianceExplained": 0.0003991896
  },
  "global_signal": {
    "Method": "Mean"
  },
  "t_comp_cor_00": {
    "CumulativeVarianceExplained": 0.1920490059,
    "Method": "tCompCor",
    "Retained": true,
    "SingularValue": 155.577994461,
    "VarianceExplained": 0.1920490059
  },
  "t_comp_cor_01": {
    "CumulativeVarianceExplained": 0.3136354285,
    "Method": "tCompCor",
    "Retained": true,
    "SingularValue": 123.789747552,
    "VarianceExplained": 0.1215864226
  },
  "t_comp_cor_02": {
    "CumulativeVarianceExplained": 0.4086626612,
    "Method": "tCompCor",
    "Retained": true,
    "SingularValue": 109.4375037008,
    "VarianceExplained": 0.0950272327
  },
  "t_comp_cor_03": {
    "CumulativeVarianceExplained": 0.4639840069,
    "Method": "tCompCor",
    "Retained": true,
    "SingularValue": 83.5003902136,
    "VarianceExplained": 0.0553213457
  },
  "t_comp_cor_04": {
    "CumulativeVarianceExplained": 0.5109862073,
    "Method": "tCompCor",
    "Retained": true,
    "SingularValue": 76.9664103754,
    "VarianceExplained": 0.0470022004
  },
  "tcompcor": {
    "Method": "Mean"
  },
  "white_matter": {
    "Method": "Mean"
  }
}